{
  "nazev_pripravku": "FERRETAB COMP. 50 mg/ 0,5 mg tvrdé tobolky",
  "slozeni": [
    {
      "nazev": "ferrosi fumaras",
      "mnozstvi": 152.10,
      "jednotky": "mg"
    },
    {
      "nazev": "acidum folicum",
      "mnozstvi": 0.50,
      "jednotky": "mg"
    }
  ],
  "ostatni_latky": [
    {
      "nazev": "Monohydrát laktózy"
    },
    {
      "nazev": "Azorubin (E122)"
    },
    {
      "nazev": "Polyakrylátová disperze 30%"
    },
    {
      "nazev": "Koloidní bezvodý oxid křemičitý"
    },
    {
      "nazev": "Magnesium-stearát"
    },
    {
      "nazev": "Mikrokrystalická celulosa"
    },
    {
      "nazev": "Chinolinová žluť (E 104)"
    },
    {
      "nazev": "Oxid titaničitý (E 171)"
    },
    {
      "nazev": "Želatina"
    }
  ],
  "kontraindikace": [
    {
      "nazev_kontraindikace": "Hypersenzitivita na léčivé látky nebo na kteroukoli pomocnou látku uvedenou v bodě 6.1."
    },
    {
      "nazev_kontraindikace": "Klinická manifestace akumulace železa: hemochromatóza, hemosideróza"
    },
    {
      "nazev_kontraindikace": "Porucha využití železa: sideroachrestická anémie, talasemie, anémie způsobená otravou olovem"
    },
    {
      "nazev_kontraindikace": "Hemoglobinopatie, hemolytická anémie, aplastická anémie, perniciózní anémie a anémie, která není odvozena od nedostatku železa nebo kyseliny listové."
    },
    {
      "nazev_kontraindikace": "Gastrointestinální poruchy"
    }
  ],
  "negativni_interakce": [
    {
      "nazev_latky": "Kyselina acetohydroxámová",
      "druh_interakce": "Snížené vstřebávání kyseliny acetohydroxámové (chelátor) a železa"
    },
    {
      "nazev_latky": "Kyselina acetylsalicylová, salicyláty, NSAR, oxyfenbutazon, fenylbutazon",
      "druh_interakce": "Zvýšené gastrointestinální dráždění"
    },
    {
      "nazev_latky": "Antacida (Al, Ca soli), přípravky s obsahem vápníku a hořčíku, kalciumbromid laktobionát,uhličitan hořečnatý zásaditý, uhličitan hořečnatý, kofein (káva a čaj), mléko a mléčné produkty, hydrogenuhličitan sodný, složky potravy (látky obsahující fytáty, oxaláty a fosfáty), měniče aniontů, polystyrolsulfonát",
      "druh_interakce": "Snížená plasmatická hladina železa"
    },
    {
      "nazev_latky": "Antiepileptika (např. karbamazepin, fenobarbital, primidon, kyselina valproová)",
      "druh_interakce": "Zvýšený příjem kyseliny listové zvyšuje aktivitu jaterních mikrosomální